chat_tokenizer/__init__.py
chat_tokenizer/chat_tokenizer.py
chat_tokenizer-0.1.0.dist-info/licenses/LICENSE
chat_tokenizer-0.1.0.dist-info/METADATA
chat_tokenizer-0.1.0.dist-info/WHEEL
chat_tokenizer-0.1.0.dist-info/top_level.txt
chat_tokenizer-0.1.0.dist-info/RECORD
