Metadata-Version: 2.4
Name: chat-tokenizer
Version: 0.1.0
Summary: Chat Tokenizer
Home-page: https://github.com/pengzhendong/chat-tokenizer
Author: Zhendong Peng
Author-email: pzd17@tsinghua.org.cn
Classifier: Programming Language :: Python :: 3
Classifier: Operating System :: OS Independent
Classifier: Topic :: Scientific/Engineering
License-File: LICENSE
Requires-Dist: torch
Dynamic: author
Dynamic: author-email
Dynamic: classifier
Dynamic: description
Dynamic: description-content-type
Dynamic: home-page
Dynamic: license-file
Dynamic: requires-dist
Dynamic: summary
